cindy/__init__.py
cindy/admin.py
cindy/forms.py
cindy/models.py
cindy/serializers.py
cindy/tasks.py
cindy/urls.py
cindy/views.py
cindy/migrations/0001_initial.py
cindy/migrations/0002_auto_20181119_2210.py
cindy/migrations/0003_auto_20181202_2347.py
cindy/migrations/__init__.py
django_cindy-0.0.3.dist-info/LICENSE.txt
django_cindy-0.0.3.dist-info/METADATA
django_cindy-0.0.3.dist-info/WHEEL
django_cindy-0.0.3.dist-info/top_level.txt
django_cindy-0.0.3.dist-info/RECORD
