Metadata-Version: 2.1
Name: django-cindy
Version: 0.0.3
Summary: UNKNOWN
Home-page: https://bitbucket.org/lullis/django_cindy
Author: UNKNOWN
Author-email: UNKNOWN
License: UNKNOWN
Keywords: django syndication feed-parsing readability
Platform: UNKNOWN
Classifier: Environment :: Web Environment
Classifier: Framework :: Django
Classifier: Operating System :: POSIX :: Linux
Classifier: Programming Language :: Python
Classifier: Programming Language :: Python :: 3.5
Classifier: Programming Language :: Python :: 3.6
Classifier: Topic :: Internet :: WWW/HTTP
Classifier: Topic :: Internet :: WWW/HTTP :: Dynamic Content
Requires-Dist: celery
Requires-Dist: dateparser
Requires-Dist: django (>=2.0)
Requires-Dist: django-boris
Requires-Dist: django-model-utils
Requires-Dist: django-taggit
Requires-Dist: feedparser
Requires-Dist: psycopg2-binary
Requires-Dist: requests
